{
  "meta": {
    "id": 262,
    "world": 5,
    "name": "Generated Level 262",
    "grid_size": [
      11,
      11
    ],
    "time_limit": 235,
    "stars": [
      10,
      20,
      30
    ]
  },
  "layout": [
    [
      0,
      0,
      0,
      1,
      0,
      0,
      1,
      1,
      1,
      0,
      0
    ],
    [
      0,
      0,
      0,
      0,
      0,
      0,
      0,
      1,
      0,
      0,
      0
    ],
    [
      0,
      1,
      0,
      0,
      1,
      0,
      0,
      1,
      0,
      0,
      0
    ],
    [
      0,
      1,
      0,
      0,
      0,
      0,
      0,
      1,
      0,
      0,
      0
    ],
    [
      0,
      0,
      0,
      0,
      0,
      0,
      1,
      0,
      0,
      0,
      0
    ],
    [
      0,
      1,
      1,
      1,
      1,
      0,
      0,
      0,
      0,
      0,
      0
    ],
    [
      0,
      0,
      0,
      0,
      1,
      0,
      0,
      0,
      0,
      0,
      0
    ],
    [
      0,
      0,
      1,
      0,
      0,
      1,
      0,
      0,
      0,
      0,
      1
    ],
    [
      0,
      0,
      1,
      0,
      0,
      0,
      0,
      0,
      0,
      0,
      0
    ],
    [
      1,
      1,
      0,
      0,
      0,
      0,
      0,
      0,
      0,
      0,
      0
    ],
    [
      1,
      0,
      0,
      0,
      0,
      0,
      0,
      0,
      0,
      0,
      0
    ]
  ],
  "blocks": [
    {
      "id": "b_0",
      "shape": "I3",
      "color": "purple",
      "counter": 6,
      "xy": [
        1,
        4
      ]
    },
    {
      "id": "b_1",
      "shape": "T4",
      "color": "green",
      "counter": 6,
      "xy": [
        5,
        8
      ]
    },
    {
      "id": "b_2",
      "shape": "O4",
      "color": "blue",
      "counter": 6,
      "xy": [
        8,
        1
      ]
    },
    {
      "id": "b_3",
      "shape": "T4",
      "color": "yellow",
      "counter": 6,
      "xy": [
        6,
        6
      ]
    },
    {
      "id": "b_4",
      "shape": "S4",
      "color": "red",
      "counter": 6,
      "xy": [
        4,
        3
      ]
    }
  ],
  "coins": {
    "static": [
      {
        "color": "purple",
        "xy": [
          2,
          3
        ]
      },
      {
        "color": "purple",
        "xy": [
          5,
          1
        ]
      },
      {
        "color": "purple",
        "xy": [
          2,
          1
        ]
      },
      {
        "color": "purple",
        "xy": [
          8,
          9
        ]
      },
      {
        "color": "purple",
        "xy": [
          9,
          3
        ]
      },
      {
        "color": "purple",
        "xy": [
          6,
          1
        ]
      },
      {
        "color": "green",
        "xy": [
          8,
          4
        ]
      },
      {
        "color": "green",
        "xy": [
          1,
          1
        ]
      },
      {
        "color": "green",
        "xy": [
          3,
          1
        ]
      },
      {
        "color": "green",
        "xy": [
          9,
          8
        ]
      },
      {
        "color": "green",
        "xy": [
          5,
          9
        ]
      },
      {
        "color": "green",
        "xy": [
          7,
          5
        ]
      },
      {
        "color": "blue",
        "xy": [
          9,
          4
        ]
      },
      {
        "color": "blue",
        "xy": [
          7,
          4
        ]
      },
      {
        "color": "blue",
        "xy": [
          4,
          8
        ]
      },
      {
        "color": "blue",
        "xy": [
          5,
          6
        ]
      },
      {
        "color": "blue",
        "xy": [
          7,
          9
        ]
      },
      {
        "color": "blue",
        "xy": [
          4,
          9
        ]
      },
      {
        "color": "yellow",
        "xy": [
          9,
          6
        ]
      },
      {
        "color": "yellow",
        "xy": [
          3,
          2
        ]
      },
      {
        "color": "yellow",
        "xy": [
          2,
          6
        ]
      },
      {
        "color": "yellow",
        "xy": [
          1,
          6
        ]
      },
      {
        "color": "yellow",
        "xy": [
          9,
          5
        ]
      },
      {
        "color": "yellow",
        "xy": [
          3,
          9
        ]
      },
      {
        "color": "red",
        "xy": [
          8,
          5
        ]
      },
      {
        "color": "red",
        "xy": [
          6,
          5
        ]
      },
      {
        "color": "red",
        "xy": [
          5,
          2
        ]
      },
      {
        "color": "red",
        "xy": [
          4,
          3
        ]
      },
      {
        "color": "red",
        "xy": [
          4,
          1
        ]
      },
      {
        "color": "red",
        "xy": [
          6,
          2
        ]
      }
    ],
    "entrances": []
  },
  "mechanics": {}
}