{
  "meta": {
    "id": 218,
    "world": 4,
    "name": "Generated Level 218",
    "grid_size": [
      11,
      11
    ],
    "time_limit": 220,
    "stars": [
      10,
      20,
      30
    ]
  },
  "layout": [
    [
      0,
      0,
      0,
      0,
      0,
      0,
      0,
      0,
      0,
      1,
      1
    ],
    [
      0,
      0,
      0,
      0,
      0,
      0,
      0,
      0,
      1,
      0,
      0
    ],
    [
      0,
      0,
      0,
      1,
      0,
      0,
      0,
      1,
      0,
      0,
      0
    ],
    [
      1,
      1,
      0,
      0,
      1,
      0,
      1,
      0,
      0,
      0,
      0
    ],
    [
      0,
      0,
      0,
      0,
      0,
      0,
      0,
      0,
      0,
      0,
      0
    ],
    [
      0,
      0,
      0,
      1,
      0,
      0,
      0,
      0,
      0,
      0,
      0
    ],
    [
      1,
      0,
      0,
      0,
      0,
      1,
      0,
      0,
      0,
      0,
      0
    ],
    [
      1,
      0,
      0,
      0,
      0,
      0,
      0,
      0,
      0,
      0,
      0
    ],
    [
      0,
      0,
      0,
      0,
      0,
      0,
      0,
      0,
      1,
      0,
      0
    ],
    [
      0,
      0,
      1,
      0,
      1,
      0,
      0,
      0,
      1,
      0,
      0
    ],
    [
      0,
      0,
      0,
      0,
      0,
      0,
      0,
      0,
      0,
      0,
      0
    ]
  ],
  "blocks": [
    {
      "id": "b_0",
      "shape": "S4",
      "color": "red",
      "counter": 5,
      "xy": [
        7,
        5
      ]
    },
    {
      "id": "b_1",
      "shape": "I2",
      "color": "purple",
      "counter": 5,
      "xy": [
        1,
        6
      ]
    },
    {
      "id": "b_2",
      "shape": "L4",
      "color": "yellow",
      "counter": 5,
      "xy": [
        1,
        0
      ]
    },
    {
      "id": "b_3",
      "shape": "L4",
      "color": "blue",
      "counter": 5,
      "xy": [
        9,
        8
      ]
    },
    {
      "id": "b_4",
      "shape": "I3",
      "color": "green",
      "counter": 5,
      "xy": [
        8,
        4
      ]
    }
  ],
  "coins": {
    "static": [
      {
        "color": "red",
        "xy": [
          3,
          3
        ]
      },
      {
        "color": "red",
        "xy": [
          2,
          4
        ]
      },
      {
        "color": "red",
        "xy": [
          7,
          5
        ]
      },
      {
        "color": "red",
        "xy": [
          9,
          6
        ]
      },
      {
        "color": "red",
        "xy": [
          1,
          9
        ]
      },
      {
        "color": "purple",
        "xy": [
          5,
          4
        ]
      },
      {
        "color": "purple",
        "xy": [
          9,
          1
        ]
      },
      {
        "color": "purple",
        "xy": [
          7,
          8
        ]
      },
      {
        "color": "purple",
        "xy": [
          4,
          8
        ]
      },
      {
        "color": "purple",
        "xy": [
          4,
          4
        ]
      },
      {
        "color": "yellow",
        "xy": [
          1,
          7
        ]
      },
      {
        "color": "yellow",
        "xy": [
          9,
          2
        ]
      },
      {
        "color": "yellow",
        "xy": [
          6,
          2
        ]
      },
      {
        "color": "yellow",
        "xy": [
          6,
          6
        ]
      },
      {
        "color": "yellow",
        "xy": [
          4,
          2
        ]
      },
      {
        "color": "blue",
        "xy": [
          8,
          3
        ]
      },
      {
        "color": "blue",
        "xy": [
          5,
          2
        ]
      },
      {
        "color": "blue",
        "xy": [
          3,
          9
        ]
      },
      {
        "color": "blue",
        "xy": [
          5,
          5
        ]
      },
      {
        "color": "blue",
        "xy": [
          9,
          7
        ]
      },
      {
        "color": "green",
        "xy": [
          2,
          7
        ]
      },
      {
        "color": "green",
        "xy": [
          6,
          1
        ]
      },
      {
        "color": "green",
        "xy": [
          7,
          7
        ]
      },
      {
        "color": "green",
        "xy": [
          3,
          7
        ]
      },
      {
        "color": "green",
        "xy": [
          8,
          2
        ]
      }
    ],
    "entrances": []
  },
  "mechanics": {}
}