{
  "meta": {
    "id": 140,
    "world": 3,
    "name": "Generated Level 140",
    "grid_size": [
      11,
      11
    ],
    "time_limit": 168,
    "stars": [
      8,
      16,
      24
    ]
  },
  "layout": [
    [
      0,
      0,
      1,
      0,
      0,
      0,
      0,
      0,
      0,
      0,
      0
    ],
    [
      0,
      0,
      0,
      0,
      0,
      0,
      0,
      0,
      0,
      0,
      0
    ],
    [
      0,
      0,
      0,
      0,
      0,
      0,
      1,
      1,
      0,
      1,
      0
    ],
    [
      0,
      0,
      0,
      0,
      0,
      0,
      1,
      0,
      0,
      1,
      0
    ],
    [
      0,
      0,
      0,
      0,
      0,
      0,
      0,
      0,
      0,
      0,
      1
    ],
    [
      0,
      0,
      0,
      0,
      0,
      0,
      0,
      0,
      0,
      0,
      0
    ],
    [
      0,
      0,
      0,
      0,
      0,
      0,
      0,
      0,
      0,
      0,
      0
    ],
    [
      0,
      0,
      0,
      0,
      0,
      0,
      0,
      0,
      1,
      0,
      0
    ],
    [
      0,
      1,
      0,
      0,
      0,
      0,
      0,
      0,
      0,
      0,
      0
    ],
    [
      0,
      0,
      0,
      0,
      0,
      0,
      1,
      0,
      0,
      0,
      0
    ],
    [
      0,
      0,
      0,
      1,
      0,
      0,
      0,
      0,
      1,
      1,
      0
    ]
  ],
  "blocks": [
    {
      "id": "b_0",
      "shape": "I3",
      "color": "yellow",
      "counter": 4,
      "xy": [
        4,
        4
      ]
    },
    {
      "id": "b_1",
      "shape": "L4",
      "color": "purple",
      "counter": 4,
      "xy": [
        0,
        3
      ]
    },
    {
      "id": "b_2",
      "shape": "I3",
      "color": "blue",
      "counter": 4,
      "xy": [
        1,
        6
      ]
    },
    {
      "id": "b_3",
      "shape": "I3",
      "color": "green",
      "counter": 4,
      "xy": [
        7,
        4
      ]
    }
  ],
  "coins": {
    "static": [
      {
        "color": "yellow",
        "xy": [
          5,
          1
        ]
      },
      {
        "color": "yellow",
        "xy": [
          8,
          8
        ]
      },
      {
        "color": "yellow",
        "xy": [
          2,
          9
        ]
      },
      {
        "color": "yellow",
        "xy": [
          1,
          7
        ]
      },
      {
        "color": "purple",
        "xy": [
          2,
          4
        ]
      },
      {
        "color": "purple",
        "xy": [
          6,
          7
        ]
      },
      {
        "color": "purple",
        "xy": [
          8,
          6
        ]
      },
      {
        "color": "purple",
        "xy": [
          5,
          9
        ]
      },
      {
        "color": "blue",
        "xy": [
          4,
          6
        ]
      },
      {
        "color": "blue",
        "xy": [
          4,
          2
        ]
      },
      {
        "color": "blue",
        "xy": [
          4,
          1
        ]
      },
      {
        "color": "blue",
        "xy": [
          3,
          4
        ]
      },
      {
        "color": "green",
        "xy": [
          3,
          1
        ]
      },
      {
        "color": "green",
        "xy": [
          7,
          8
        ]
      },
      {
        "color": "green",
        "xy": [
          3,
          9
        ]
      },
      {
        "color": "green",
        "xy": [
          2,
          8
        ]
      }
    ],
    "entrances": []
  },
  "mechanics": {}
}