{
  "meta": {
    "id": 108,
    "world": 2,
    "name": "Generated Level 108",
    "grid_size": [
      11,
      11
    ],
    "time_limit": 205,
    "stars": [
      10,
      20,
      30
    ]
  },
  "layout": [
    [
      1,
      0,
      0,
      0,
      0,
      0,
      0,
      0,
      0,
      0,
      1
    ],
    [
      0,
      0,
      0,
      0,
      0,
      0,
      0,
      0,
      0,
      1,
      1
    ],
    [
      0,
      0,
      1,
      0,
      0,
      0,
      0,
      0,
      1,
      0,
      0
    ],
    [
      1,
      1,
      1,
      0,
      0,
      0,
      0,
      0,
      0,
      0,
      0
    ],
    [
      0,
      1,
      0,
      0,
      1,
      0,
      0,
      1,
      0,
      0,
      0
    ],
    [
      0,
      0,
      0,
      0,
      0,
      1,
      1,
      0,
      0,
      0,
      0
    ],
    [
      0,
      0,
      0,
      0,
      1,
      0,
      0,
      0,
      0,
      0,
      0
    ],
    [
      0,
      0,
      0,
      0,
      1,
      0,
      0,
      0,
      0,
      0,
      0
    ],
    [
      0,
      0,
      0,
      1,
      0,
      0,
      0,
      0,
      0,
      0,
      0
    ],
    [
      0,
      0,
      0,
      0,
      0,
      0,
      0,
      0,
      0,
      0,
      0
    ],
    [
      0,
      0,
      1,
      0,
      0,
      0,
      0,
      0,
      0,
      0,
      0
    ]
  ],
  "blocks": [
    {
      "id": "b_0",
      "shape": "I3",
      "color": "green",
      "counter": 4,
      "xy": [
        8,
        6
      ]
    },
    {
      "id": "b_1",
      "shape": "T4",
      "color": "yellow",
      "counter": 4,
      "xy": [
        5,
        3
      ]
    },
    {
      "id": "b_2",
      "shape": "I2",
      "color": "red",
      "counter": 4,
      "xy": [
        3,
        9
      ]
    },
    {
      "id": "b_3",
      "shape": "O4",
      "color": "blue",
      "counter": 4,
      "xy": [
        0,
        9
      ]
    },
    {
      "id": "b_4",
      "shape": "I2",
      "color": "purple",
      "counter": 4,
      "xy": [
        4,
        1
      ]
    }
  ],
  "coins": {
    "static": [
      {
        "color": "green",
        "xy": [
          3,
          2
        ]
      },
      {
        "color": "green",
        "xy": [
          1,
          7
        ]
      },
      {
        "color": "green",
        "xy": [
          5,
          7
        ]
      },
      {
        "color": "green",
        "xy": [
          7,
          2
        ]
      },
      {
        "color": "yellow",
        "xy": [
          9,
          7
        ]
      },
      {
        "color": "yellow",
        "xy": [
          6,
          6
        ]
      },
      {
        "color": "yellow",
        "xy": [
          4,
          3
        ]
      },
      {
        "color": "yellow",
        "xy": [
          9,
          4
        ]
      },
      {
        "color": "red",
        "xy": [
          7,
          8
        ]
      },
      {
        "color": "red",
        "xy": [
          3,
          5
        ]
      },
      {
        "color": "red",
        "xy": [
          9,
          9
        ]
      },
      {
        "color": "red",
        "xy": [
          7,
          7
        ]
      },
      {
        "color": "blue",
        "xy": [
          5,
          8
        ]
      },
      {
        "color": "blue",
        "xy": [
          1,
          2
        ]
      },
      {
        "color": "blue",
        "xy": [
          5,
          6
        ]
      },
      {
        "color": "blue",
        "xy": [
          1,
          5
        ]
      },
      {
        "color": "purple",
        "xy": [
          7,
          1
        ]
      },
      {
        "color": "purple",
        "xy": [
          2,
          8
        ]
      },
      {
        "color": "purple",
        "xy": [
          3,
          7
        ]
      },
      {
        "color": "purple",
        "xy": [
          1,
          6
        ]
      }
    ],
    "entrances": []
  },
  "mechanics": {}
}